{"nm":"ripple","ddd":0,"h":46,"w":46,"meta":{"g":"LottieFiles Figma v96"},"layers":[{"ty":0,"nm":"Frame 1272628730","sr":1,"st":0,"op":103.12,"ip":0,"hd":false,"ddd":0,"bm":0,"hasMask":false,"ao":0,"ks":{"a":{"a":0,"k":[16,16]},"s":{"a":0,"k":[100,100]},"sk":{"a":0,"k":0},"p":{"a":0,"k":[23,23]},"r":{"a":0,"k":0},"sa":{"a":0,"k":0},"o":{"a":0,"k":100}},"w":46,"h":46,"refId":"1","ind":1},{"ty":4,"nm":"Ellipse 2220","sr":1,"st":0,"op":103.12,"ip":0,"hd":false,"ddd":0,"bm":0,"hasMask":false,"ao":0,"ks":{"a":{"a":1,"k":[{"o":{"x":0.33,"y":1},"i":{"x":0.68,"y":1},"s":[21,21],"t":0},{"o":{"x":0.33,"y":1},"i":{"x":0.68,"y":1},"s":[14.5,14.5],"t":18},{"o":{"x":0.33,"y":1},"i":{"x":0.68,"y":1},"s":[22,22],"t":36},{"o":{"x":0.33,"y":1},"i":{"x":0.68,"y":1},"s":[22,22],"t":84},{"s":[21,21],"t":102}]},"s":{"a":0,"k":[100,100]},"sk":{"a":0,"k":0},"p":{"a":0,"k":[23,23]},"r":{"a":0,"k":0},"sa":{"a":0,"k":0},"o":{"a":0,"k":50}},"shapes":[{"ty":"sh","bm":0,"hd":false,"nm":"","d":1,"ks":{"a":1,"k":[{"o":{"x":0.33,"y":1},"i":{"x":0.68,"y":1},"s":[{"c":true,"i":[[0,0],[11.6,0],[0,11.6],[-11.6,0],[0,-11.6]],"o":[[0,11.6],[-11.6,0],[0,-11.6],[11.6,0],[0,0]],"v":[[42,21],[21,42],[0,21],[21,0],[42,21]]}],"t":0},{"o":{"x":0.33,"y":1},"i":{"x":0.68,"y":1},"s":[{"c":true,"i":[[0,0],[8.01,0],[0,8.01],[-8.01,0],[0,-8.01]],"o":[[0,8.01],[-8.01,0],[0,-8.01],[8.01,0],[0,0]],"v":[[29,14.5],[14.5,29],[0,14.5],[14.5,0],[29,14.5]]}],"t":18},{"o":{"x":0.33,"y":1},"i":{"x":0.68,"y":1},"s":[{"c":true,"i":[[0,0],[12.15,0],[0,12.15],[-12.15,0],[0,-12.15]],"o":[[0,12.15],[-12.15,0],[0,-12.15],[12.15,0],[0,0]],"v":[[44,22],[22,44],[0,22],[22,0],[44,22]]}],"t":36},{"o":{"x":0.33,"y":1},"i":{"x":0.68,"y":1},"s":[{"c":true,"i":[[0,0],[12.15,0],[0,12.15],[-12.15,0],[0,-12.15]],"o":[[0,12.15],[-12.15,0],[0,-12.15],[12.15,0],[0,0]],"v":[[44,22],[22,44],[0,22],[22,0],[44,22]]}],"t":84},{"s":[{"c":true,"i":[[0,0],[11.6,0],[0,11.6],[-11.6,0],[0,-11.6]],"o":[[0,11.6],[-11.6,0],[0,-11.6],[11.6,0],[0,0]],"v":[[42,21],[21,42],[0,21],[21,0],[42,21]]}],"t":102}]}},{"ty":"fl","bm":0,"hd":false,"nm":"","c":{"a":0,"k":[0.3044,0.7265,0.2973]},"r":1,"o":{"a":0,"k":48}}],"ind":2},{"ty":4,"nm":"Ellipse 2219","sr":1,"st":0,"op":103.12,"ip":0,"hd":false,"ddd":0,"bm":0,"hasMask":false,"ao":0,"ks":{"a":{"a":1,"k":[{"o":{"x":0.33,"y":1},"i":{"x":0.68,"y":1},"s":[18,18],"t":0},{"o":{"x":0.33,"y":1},"i":{"x":0.68,"y":1},"s":[19.5,19.5],"t":18},{"o":{"x":0.33,"y":1},"i":{"x":0.68,"y":1},"s":[19,19],"t":36},{"o":{"x":0.33,"y":1},"i":{"x":0.68,"y":1},"s":[19,19],"t":84},{"s":[18,18],"t":102}]},"s":{"a":0,"k":[100,100]},"sk":{"a":0,"k":0},"p":{"a":0,"k":[23,23]},"r":{"a":0,"k":0},"sa":{"a":0,"k":0},"o":{"a":0,"k":70}},"shapes":[{"ty":"sh","bm":0,"hd":false,"nm":"","d":1,"ks":{"a":1,"k":[{"o":{"x":0.33,"y":1},"i":{"x":0.68,"y":1},"s":[{"c":true,"i":[[0,0],[9.94,0],[0,9.94],[-9.94,0],[0,-9.94]],"o":[[0,9.94],[-9.94,0],[0,-9.94],[9.94,0],[0,0]],"v":[[36,18],[18,36],[0,18],[18,0],[36,18]]}],"t":0},{"o":{"x":0.33,"y":1},"i":{"x":0.68,"y":1},"s":[{"c":true,"i":[[0,0],[10.77,0],[0,10.77],[-10.77,0],[0,-10.77]],"o":[[0,10.77],[-10.77,0],[0,-10.77],[10.77,0],[0,0]],"v":[[39,19.5],[19.5,39],[0,19.5],[19.5,0],[39,19.5]]}],"t":18},{"o":{"x":0.33,"y":1},"i":{"x":0.68,"y":1},"s":[{"c":true,"i":[[0,0],[10.49,0],[0,10.49],[-10.49,0],[0,-10.49]],"o":[[0,10.49],[-10.49,0],[0,-10.49],[10.49,0],[0,0]],"v":[[38,19],[19,38],[0,19],[19,0],[38,19]]}],"t":36},{"o":{"x":0.33,"y":1},"i":{"x":0.68,"y":1},"s":[{"c":true,"i":[[0,0],[10.49,0],[0,10.49],[-10.49,0],[0,-10.49]],"o":[[0,10.49],[-10.49,0],[0,-10.49],[10.49,0],[0,0]],"v":[[38,19],[19,38],[0,19],[19,0],[38,19]]}],"t":84},{"s":[{"c":true,"i":[[0,0],[9.94,0],[0,9.94],[-9.94,0],[0,-9.94]],"o":[[0,9.94],[-9.94,0],[0,-9.94],[9.94,0],[0,0]],"v":[[36,18],[18,36],[0,18],[18,0],[36,18]]}],"t":102}]}},{"ty":"fl","bm":0,"hd":false,"nm":"","c":{"a":0,"k":[0.3044,0.7265,0.2973]},"r":1,"o":{"a":0,"k":100}}],"ind":3}],"v":"5.7.0","fr":60,"op":102.12,"ip":0,"assets":[{"nm":"[Asset] Frame 1272628730","id":"1","layers":[{"ty":0,"nm":"mic","sr":1,"st":0,"op":103.12,"ip":0,"hd":false,"ddd":0,"bm":0,"hasMask":true,"ao":0,"ks":{"a":{"a":0,"k":[10,10]},"s":{"a":0,"k":[100,100]},"sk":{"a":0,"k":0},"p":{"a":0,"k":[16.29,16.29]},"r":{"a":0,"k":0},"sa":{"a":0,"k":0},"o":{"a":0,"k":100}},"masksProperties":[{"nm":"","inv":false,"mode":"a","x":{"a":0,"k":0},"o":{"a":0,"k":100},"pt":{"a":1,"k":[{"o":{"x":0.33,"y":1},"i":{"x":0.68,"y":1},"s":[{"c":true,"i":[[0,0],[0,0],[0,0],[0,0]],"o":[[0,0],[0,0],[0,0],[0,0]],"v":[[20,0],[20,20],[0,20],[0,0]]}],"t":0},{"o":{"x":0.33,"y":1},"i":{"x":0.68,"y":1},"s":[{"c":true,"i":[[0,0],[0,0],[0,0],[0,0]],"o":[[0,0],[0,0],[0,0],[0,0]],"v":[[20,0],[20,20],[0,20],[0,0]]}],"t":18},{"o":{"x":0.33,"y":1},"i":{"x":0.68,"y":1},"s":[{"c":true,"i":[[0,0],[0,0],[0,0],[0,0]],"o":[[0,0],[0,0],[0,0],[0,0]],"v":[[20,0],[20,20],[0,20],[0,0]]}],"t":36},{"o":{"x":0.33,"y":1},"i":{"x":0.68,"y":1},"s":[{"c":true,"i":[[0,0],[0,0],[0,0],[0,0]],"o":[[0,0],[0,0],[0,0],[0,0]],"v":[[20,0],[20,20],[0,20],[0,0]]}],"t":84},{"s":[{"c":true,"i":[[0,0],[0,0],[0,0],[0,0]],"o":[[0,0],[0,0],[0,0],[0,0]],"v":[[20,0],[20,20],[0,20],[0,0]]}],"t":102}]}}],"w":46,"h":46,"refId":"2","ind":1},{"ty":4,"nm":"Frame 1272628730 Bg","sr":1,"st":0,"op":103.12,"ip":0,"hd":false,"ddd":0,"bm":0,"hasMask":false,"ao":0,"ks":{"a":{"a":0,"k":[16,16]},"s":{"a":0,"k":[100,100]},"sk":{"a":0,"k":0},"p":{"a":0,"k":[16,16]},"r":{"a":0,"k":0},"sa":{"a":0,"k":0},"o":{"a":0,"k":100}},"shapes":[{"ty":"sh","bm":0,"hd":false,"nm":"","d":1,"ks":{"a":0,"k":{"c":true,"i":[[0,-8.63],[0,0],[8.63,0],[0,0],[0,8.63],[0,0],[-8.63,0],[0,0]],"o":[[0,0],[0,8.63],[0,0],[-8.63,0],[0,0],[0,-8.63],[0,0],[8.63,0]],"v":[[32,15.63],[32,16.37],[16.37,32],[15.63,32],[0,16.37],[0,15.63],[15.63,0],[16.37,0]]}}},{"ty":"fl","bm":0,"hd":false,"nm":"","c":{"a":0,"k":[0.2271,0.567,0.2213]},"r":1,"o":{"a":0,"k":100}}],"ind":2}]},{"nm":"[Asset] mic","id":"2","layers":[{"ty":4,"nm":"Page-1","sr":1,"st":0,"op":103.12,"ip":0,"hd":false,"ddd":0,"bm":0,"hasMask":false,"ao":0,"ks":{"a":{"a":0,"k":[10,10]},"s":{"a":0,"k":[100,100]},"sk":{"a":0,"k":0},"p":{"a":0,"k":[10,10]},"r":{"a":0,"k":0},"sa":{"a":0,"k":0},"o":{"a":0,"k":100}},"shapes":[],"ind":1},{"ty":4,"nm":"Mic","sr":1,"st":0,"op":103.12,"ip":0,"hd":false,"ddd":0,"bm":0,"hasMask":false,"ao":0,"ks":{"a":{"a":0,"k":[10,10]},"s":{"a":0,"k":[100,100]},"sk":{"a":0,"k":0},"p":{"a":0,"k":[10,10]},"r":{"a":0,"k":0},"sa":{"a":0,"k":0},"o":{"a":0,"k":100}},"shapes":[],"ind":2,"parent":1},{"ty":4,"nm":"Path","sr":1,"st":0,"op":103.12,"ip":0,"hd":false,"ddd":0,"bm":0,"hasMask":false,"ao":0,"ks":{"a":{"a":0,"k":[5.83,2.92]},"s":{"a":0,"k":[100,100]},"sk":{"a":0,"k":0},"p":{"a":0,"k":[10,12.08]},"r":{"a":0,"k":0},"sa":{"a":0,"k":0},"o":{"a":0,"k":100}},"shapes":[{"ty":"sh","bm":0,"hd":false,"nm":"","d":1,"ks":{"a":0,"k":{"c":false,"i":[[0,0],[3.22,0],[0,3.22]],"o":[[0,3.22],[-3.22,0],[0,0]],"v":[[11.67,0],[5.83,5.83],[0,0]]}}},{"ty":"st","bm":0,"hd":false,"nm":"","lc":2,"lj":1,"ml":4,"o":{"a":0,"k":100},"w":{"a":1,"k":[{"o":{"x":0.33,"y":1},"i":{"x":0.68,"y":1},"s":[1.6666673421859741],"t":0},{"o":{"x":0.33,"y":1},"i":{"x":0.68,"y":1},"s":[1.6666673421859741],"t":18},{"o":{"x":0.33,"y":1},"i":{"x":0.68,"y":1},"s":[1.6666673421859741],"t":36},{"o":{"x":0.33,"y":1},"i":{"x":0.68,"y":1},"s":[1.6666673421859741],"t":84},{"s":[1.6666673421859741],"t":102}]},"c":{"a":0,"k":[1,1,1]}}],"ind":3,"parent":2},{"ty":4,"nm":"Path","sr":1,"st":0,"op":103.12,"ip":0,"hd":false,"ddd":0,"bm":0,"hasMask":false,"ao":0,"ks":{"a":{"a":0,"k":[3.33,0]},"s":{"a":0,"k":[100,100]},"sk":{"a":0,"k":0},"p":{"a":0,"k":[10,17.49]},"r":{"a":0,"k":0},"sa":{"a":0,"k":0},"o":{"a":0,"k":100}},"shapes":[{"ty":"sh","bm":0,"hd":false,"nm":"","d":1,"ks":{"a":0,"k":{"c":true,"i":[[0,0],[0,-0.46],[-0.46,0],[0,0],[0,0]],"o":[[-0.46,0],[0,0.46],[0,0],[0,0],[0,0]],"v":[[0,-0.83],[-0.83,0],[0,0.83],[0,0],[0,-0.83]]}}},{"ty":"sh","bm":0,"hd":false,"nm":"","d":1,"ks":{"a":0,"k":{"c":true,"i":[[0,0],[0,0.46],[0.46,0],[0,0],[0,0]],"o":[[0.46,0],[0,-0.46],[0,0],[0,0],[0,0]],"v":[[6.67,0.83],[7.5,0],[6.67,-0.83],[6.67,0],[6.67,0.83]]}}},{"ty":"sh","bm":0,"hd":false,"nm":"","d":1,"ks":{"a":0,"k":{"c":true,"i":[[0,0],[0,0],[0,0],[0,0],[0,0],[0,0],[0,0]],"o":[[0,0],[0,0],[0,0],[0,0],[0,0],[0,0],[0,0]],"v":[[0,0],[0,0.83],[6.67,0.83],[6.67,0],[6.67,-0.83],[0,-0.83],[0,0]]}}},{"ty":"fl","bm":0,"hd":false,"nm":"","c":{"a":0,"k":[1,1,1]},"r":1,"o":{"a":0,"k":100}}],"ind":4,"parent":2},{"ty":4,"nm":"Path","sr":1,"st":0,"op":103.12,"ip":0,"hd":false,"ddd":0,"bm":0,"hasMask":false,"ao":0,"ks":{"a":{"a":0,"k":[0,1.25]},"s":{"a":0,"k":[100,100]},"sk":{"a":0,"k":0},"p":{"a":0,"k":[9.99,16.24]},"r":{"a":0,"k":0},"sa":{"a":0,"k":0},"o":{"a":0,"k":100}},"shapes":[{"ty":"sh","bm":0,"hd":false,"nm":"","d":1,"ks":{"a":0,"k":{"c":true,"i":[[0,0],[0.46,0],[0,-0.46],[0,0],[0,0]],"o":[[0,-0.46],[-0.46,0],[0,0],[0,0],[0,0]],"v":[[0.83,0],[0,-0.83],[-0.83,0],[0,0],[0.83,0]]}}},{"ty":"sh","bm":0,"hd":false,"nm":"","d":1,"ks":{"a":0,"k":{"c":true,"i":[[0,0],[-0.46,0],[0,0.46],[0,0],[0,0]],"o":[[0,0.46],[0.46,0],[0,0],[0,0],[0,0]],"v":[[-0.83,2.5],[0,3.33],[0.83,2.5],[0,2.5],[-0.83,2.5]]}}},{"ty":"sh","bm":0,"hd":false,"nm":"","d":1,"ks":{"a":0,"k":{"c":true,"i":[[0,0],[0,0],[0,0],[0,0],[0,0],[0,0],[0,0]],"o":[[0,0],[0,0],[0,0],[0,0],[0,0],[0,0],[0,0]],"v":[[0,0],[-0.83,0],[-0.83,2.5],[0,2.5],[0.83,2.5],[0.83,0],[0,0]]}}},{"ty":"fl","bm":0,"hd":false,"nm":"","c":{"a":0,"k":[1,1,1]},"r":1,"o":{"a":0,"k":100}}],"ind":5,"parent":2},{"ty":4,"nm":"Rectangle","sr":1,"st":0,"op":103.12,"ip":0,"hd":false,"ddd":0,"bm":0,"hasMask":false,"ao":0,"ks":{"a":{"a":0,"k":[2.5,4.58]},"s":{"a":0,"k":[100,100]},"sk":{"a":0,"k":0},"p":{"a":0,"k":[10,7.08]},"r":{"a":0,"k":0},"sa":{"a":0,"k":0},"o":{"a":0,"k":100}},"shapes":[{"ty":"sh","bm":0,"hd":false,"nm":"","d":1,"ks":{"a":0,"k":{"c":true,"i":[[0,0],[1.38,0],[0,-1.38],[0,0],[-1.38,0],[0,1.38],[0,0]],"o":[[0,-1.38],[-1.38,0],[0,0],[0,1.38],[1.38,0],[0,0],[0,0]],"v":[[5,2.5],[2.5,0],[0,2.5],[0,6.67],[2.5,9.17],[5,6.67],[5,2.5]]}}},{"ty":"st","bm":0,"hd":false,"nm":"","lc":2,"lj":1,"ml":4,"o":{"a":0,"k":100},"w":{"a":1,"k":[{"o":{"x":0.33,"y":1},"i":{"x":0.68,"y":1},"s":[1.6666673421859741],"t":0},{"o":{"x":0.33,"y":1},"i":{"x":0.68,"y":1},"s":[1.6666673421859741],"t":18},{"o":{"x":0.33,"y":1},"i":{"x":0.68,"y":1},"s":[1.6666673421859741],"t":36},{"o":{"x":0.33,"y":1},"i":{"x":0.68,"y":1},"s":[1.6666673421859741],"t":84},{"s":[1.6666673421859741],"t":102}]},"c":{"a":0,"k":[1,1,1]}},{"ty":"fl","bm":0,"hd":false,"nm":"","c":{"a":0,"k":[1,1,1]},"r":1,"o":{"a":0,"k":100}}],"ind":6,"parent":2},{"ty":4,"nm":"Rectangle","sr":1,"st":0,"op":103.12,"ip":0,"hd":false,"ddd":0,"bm":0,"hasMask":false,"ao":0,"ks":{"a":{"a":0,"k":[10,10]},"s":{"a":0,"k":[100,100]},"sk":{"a":0,"k":0},"p":{"a":0,"k":[10,10]},"r":{"a":0,"k":0},"sa":{"a":0,"k":0},"o":{"a":0,"k":100}},"shapes":[{"ty":"sh","bm":0,"hd":false,"nm":"","d":1,"ks":{"a":0,"k":{"c":true,"i":[[0,0],[0,0],[0,0],[0,0],[0,0]],"o":[[0,0],[0,0],[0,0],[0,0],[0,0]],"v":[[20,0],[0,0],[0,20],[20,20],[20,0]]}}}],"ind":7,"parent":2},{"ty":4,"nm":"mic Bg","sr":1,"st":0,"op":103.12,"ip":0,"hd":false,"ddd":0,"bm":0,"hasMask":false,"ao":0,"ks":{"a":{"a":0,"k":[10,10]},"s":{"a":0,"k":[100,100]},"sk":{"a":0,"k":0},"p":{"a":0,"k":[10,10]},"r":{"a":0,"k":0},"sa":{"a":0,"k":0},"o":{"a":0,"k":100}},"shapes":[{"ty":"sh","bm":0,"hd":false,"nm":"","d":1,"ks":{"a":0,"k":{"c":true,"i":[[0,0],[0,0],[0,0],[0,0]],"o":[[0,0],[0,0],[0,0],[0,0]],"v":[[20,0],[20,20],[0,20],[0,0]]}}},{"ty":"fl","bm":0,"hd":false,"nm":"","c":{"a":0,"k":[1,1,1]},"r":1,"o":{"a":0,"k":0}}],"ind":8}]}]}